Metadata-Version: 2.1
Name: nataili
Version: 0.3.4
Summary: Nataili: Multimodal AI Python Library
Author-email: hlky <goto@github.com>
License: GNU AFFERO GENERAL PUBLIC LICENSE
Project-URL: Homepage, https://github.com/db0/nataili
Project-URL: Bug Tracker, https://github.com/db0/nataili/issues
Classifier: Programming Language :: Python :: 3
Classifier: License :: OSI Approved :: GNU Affero General Public License v3
Classifier: Operating System :: OS Independent
Requires-Python: >=3.8
License-File: LICENSE
Requires-Dist: torch (==1.13.1)
Requires-Dist: torchvision
Requires-Dist: torchaudio
Requires-Dist: taming-transformers-rom1504
Requires-Dist: k-diffusion
Requires-Dist: omegaconf
Requires-Dist: diffusers
Requires-Dist: fairscale
Requires-Dist: tqdm
Requires-Dist: python-slugify
Requires-Dist: einops
Requires-Dist: facexlib
Requires-Dist: kornia
Requires-Dist: opencv-python-headless
Requires-Dist: basicsr
Requires-Dist: gfpgan
Requires-Dist: realesrgan
Requires-Dist: loguru
Requires-Dist: pydantic
Requires-Dist: bitsandbytes
Requires-Dist: transformers
Requires-Dist: open-clip-torch
Requires-Dist: pytorch-lightning
Requires-Dist: accelerate
Requires-Dist: ray
Requires-Dist: webdataset
Requires-Dist: safetensors
Requires-Dist: prettytable
